ARCCSSive/__init__.py
ARCCSSive/data.py
ARCCSSive/debug.py
ARCCSSive/pkg_info.py
ARCCSSive/CMIP5/DB.py
ARCCSSive/CMIP5/Model.py
ARCCSSive/CMIP5/__init__.py
ARCCSSive/CMIP5/compare_helpers.py
ARCCSSive/CMIP5/other_functions.py
ARCCSSive/CMIP5/pyesgf_functions.py
ARCCSSive/CMIP5/update_db_functions.py
ARCCSSive/cli/__init__.py
ARCCSSive/cli/compare_ESGF.py
ARCCSSive/cli/search_replica.py
ARCCSSive/data/cmip_dict_pickle
ARCCSSive-0.3.3.dist-info/DESCRIPTION.rst
ARCCSSive-0.3.3.dist-info/METADATA
ARCCSSive-0.3.3.dist-info/RECORD
ARCCSSive-0.3.3.dist-info/WHEEL
ARCCSSive-0.3.3.dist-info/metadata.json
ARCCSSive-0.3.3.dist-info/pbr.json
ARCCSSive-0.3.3.dist-info/top_level.txt
