Metadata-Version: 2.0
Name: ARCCSSive
Version: 0.3.3
Summary: ARCCSS Data Archive Tools
Home-page: UNKNOWN
Author: Scott Wales
Author-email: scott.wales@unimelb.edu.au
License: UNKNOWN
Platform: UNKNOWN
Classifier: Development Status :: 3 - Alpha
Classifier: Environment :: Console
Classifier: Intended Audience :: Science/Research
Classifier: License :: OSI Approved :: Apache Software License
Classifier: Operating System :: POSIX :: Linux
Classifier: Programming Language :: Python :: 2.6
Classifier: Programming Language :: Python :: 2.7
Classifier: Programming Language :: Python :: 3.5
Requires-Dist: SQLAlchemy
Requires-Dist: esgf-pyclient (>=0.1.8)
Requires-Dist: six
Provides-Extra: dev
Requires-Dist: mock; extra == 'dev'
Requires-Dist: pytest; extra == 'dev'
Requires-Dist: recommonmark; extra == 'dev'
Requires-Dist: sphinx; extra == 'dev'
